sepsolve/__init__.py
sepsolve/sepsolve.py
sepsolve/sepsolve_base.py
sepsolve/sepsolve_fixed.py
sepsolve/sepsolve_param_opt.py
sepsolve-0.1.1.dist-info/licenses/LICENSE
sepsolve-0.1.1.dist-info/METADATA
sepsolve-0.1.1.dist-info/WHEEL
sepsolve-0.1.1.dist-info/top_level.txt
sepsolve-0.1.1.dist-info/RECORD
