Metadata-Version: 2.4
Name: sepsolve
Version: 0.1.1
Summary: Marker gene selection module
Home-page: https://github.com/bborozan/SepSolve
Author: Bartol Borozan
Author-email: bborozan@mathos.hr
License: MIT
License-File: LICENSE
Requires-Dist: gurobipy
Requires-Dist: pandas
Requires-Dist: scipy
Requires-Dist: numpy
Requires-Dist: scikit-learn
Dynamic: author
Dynamic: author-email
Dynamic: description
Dynamic: description-content-type
Dynamic: home-page
Dynamic: license
Dynamic: license-file
Dynamic: requires-dist
Dynamic: summary
